tkitSeq2seq/__init__.py
tkitSeq2seq/decoder.py
tkitSeq2seq/encoder.py
tkitSeq2seq/model.py
tkitSeq2seq/trainer.py
tkitSeq2seq-0.0.0.3.dist-info/LICENSE
tkitSeq2seq-0.0.0.3.dist-info/METADATA
tkitSeq2seq-0.0.0.3.dist-info/WHEEL
tkitSeq2seq-0.0.0.3.dist-info/top_level.txt
tkitSeq2seq-0.0.0.3.dist-info/RECORD
