Metadata-Version: 2.1
Name: tkitSeq2seq
Version: 0.0.0.3
Summary: Terry toolkit tkitSeq2seq
Home-page: http://www.terrychan.org/tkit-seq2seq/
Author: Terry Chan
Author-email: napoler2008@gmail.com
License: UNKNOWN
Platform: UNKNOWN
Requires-Dist: tqdm (==4.62.1)
Requires-Dist: torchmetrics (==0.5.0)
Requires-Dist: pytorch-lightning (>=1.4.2)
